utdee_backend/__init__.py
utdee_backend/api/__init__.py
utdee_backend/api/entry_.py
utdee_backend/api/main_page_.py
utdee_backend/api/spark_task_.py
utdee_backend/api/thread_task_.py
utdee_backend/context/__init__.py
utdee_backend/context/settings.py
utdee_backend/tasks_manager/__init__.py
utdee_backend/tasks_manager/api/__init__.py
utdee_backend/tasks_manager/api/tasks.py
utdee_backend/tasks_manager/dispather/__init__.py
utdee_backend/tasks_manager/dispather/abstract.py
utdee_backend/tasks_manager/dispather/process_pool_based.py
utdee_backend/tasks_manager/dispather/spark_based.py
utdee_backend/tasks_manager/dispather/thread_pool_based.py
utdee_backend/tasks_manager/factory/__init__.py
utdee_backend/tasks_manager/factory/abstract.py
utdee_backend/tasks_manager/factory/list_of_tasks.py
utdee_backend/tasks_manager/manager.py
utdee_backend/tasks_manager/task/__init__.py
utdee_backend/tasks_manager/task/abstract.py
utdee_backend/tasks_manager/task/requests_based.py
utdee_backend/utils/__init__.py
utdee_backend/utils/async_generator_descryptor.py
utdee_backend/utils/context_manager.py
utdee_backend/utils/singleton.py
utdee_backend/utils/trace.py
utdee_backend-0.1.0.dist-info/METADATA
utdee_backend-0.1.0.dist-info/WHEEL
utdee_backend-0.1.0.dist-info/RECORD
